[
  {
    "id": "4f5a0176-f3e0-470c-b3e5-78884290cd75",
    "data": [
      {
        "text": "module ",
        "userDefined": false
      },
      {
        "text": "4",
        "meta": "@sys.number",
        "alias": "number",
        "userDefined": false
      },
      {
        "text": ", ",
        "userDefined": false
      },
      {
        "text": "unique identifier",
        "meta": "@quiz3",
        "alias": "quiz3",
        "userDefined": true
      },
      {
        "text": ", ",
        "userDefined": false
      },
      {
        "text": "email messages",
        "meta": "@quiz3",
        "alias": "quiz31",
        "userDefined": true
      },
      {
        "text": ", ",
        "userDefined": false
      },
      {
        "text": "block unwanted",
        "meta": "@quiz3",
        "alias": "quiz32",
        "userDefined": true
      },
      {
        "text": ", ",
        "userDefined": false
      },
      {
        "text": "whatsapp",
        "meta": "@quiz3",
        "alias": "quiz33",
        "userDefined": true
      },
      {
        "text": ", ",
        "userDefined": false
      },
      {
        "text": "identity theft",
        "meta": "@quiz3",
        "alias": "quiz34",
        "userDefined": true
      }
    ],
    "isTemplate": false,
    "count": 0,
    "lang": "en",
    "updated": 0
  },
  {
    "id": "35be8c99-d479-4dee-bee0-c3270d4a74ef",
    "data": [
      {
        "text": "Module ",
        "userDefined": false
      },
      {
        "text": "4",
        "meta": "@sys.number",
        "alias": "number",
        "userDefined": false
      }
    ],
    "isTemplate": false,
    "count": 0,
    "lang": "en",
    "updated": 0
  }
]